datapoint/Forecast.py
datapoint/Manager.py
datapoint/__init__.py
datapoint/exceptions.py
datapoint/weather_codes.py
datapoint-0.13.0.dist-info/METADATA
datapoint-0.13.0.dist-info/WHEEL
datapoint-0.13.0.dist-info/licenses/LICENSE
datapoint-0.13.0.dist-info/RECORD
