Metadata-Version: 2.4
Name: datapoint
Version: 0.13.0
Summary: Python interface to the Met Office's Datapoint API
Project-URL: Homepage, https://github.com/Perseudonymous/datapoint-python
Project-URL: Documentation, http://datapoint-python.readthedocs.org/en/latest
Author: Jacob Tomlinson
Author-email: Emily Price <emily.j.price.nth@gmail.com>
License: GNU GENERAL PUBLIC LICENSE
License-File: LICENSE
Keywords: DataHub,Met Office,weather,weather forecast
Classifier: Development Status :: 3 - Alpha
Classifier: License :: OSI Approved :: GNU General Public License v3 (GPLv3)
Classifier: Programming Language :: Python :: 3
Classifier: Programming Language :: Python :: 3.9
Classifier: Programming Language :: Python :: 3.10
Classifier: Programming Language :: Python :: 3.11
Classifier: Programming Language :: Python :: 3.12
Requires-Python: >=3.9
Requires-Dist: appdirs<2,>=1
Requires-Dist: geojson<4,>=3.0.0
Requires-Dist: requests<3,>=2.20.0
